tboulet_test_package890/__init__.py
tboulet_test_package890/file1.py
tboulet_test_package890-0.0.4.dist-info/METADATA
tboulet_test_package890-0.0.4.dist-info/WHEEL
tboulet_test_package890-0.0.4.dist-info/top_level.txt
tboulet_test_package890-0.0.4.dist-info/RECORD
