Metadata-Version: 2.1
Name: tboulet-test-package890
Version: 0.0.4
Summary: My first Python package
Home-page: https://github.com/tboulet/Python-Tips-And-Tools
Author: T. B.
Author-email: dummy@gmail.com
License: MIT
